[
    {
        "card_id": "ageless-crone",
        "flavor": "\"It is good to see you again, Grandmother. You have not aged a day. Ever.\" – Ikoma Ikehata",
        "illustrator": "Lin Hsiang",
        "image_url": "http://lcg-cdn.fantasyflightgames.com/l5r/L5C04_53.jpg",
        "octgn_id": "c90bca27-60b9-41ef-bdb9-b11b70dc3109",
        "position": "53",
        "quantity": 3
    },
    {
        "card_id": "back-alley-hideaway",
        "flavor": null,
        "illustrator": "Niten",
        "image_url": "http://lcg-cdn.fantasyflightgames.com/l5r/L5C04_47.jpg",
        "octgn_id": "b6111945-6e48-463b-8f7f-acb8035a9faf",
        "position": "47",
        "quantity": 3
    },
    {
        "card_id": "bayushi-kachiko",
        "flavor": "\"Which of us would bid this game to end? We are nearly perfectly matched, but there can be only one victor.\"",
        "illustrator": "Polar Engine",
        "image_url": "http://lcg-cdn.fantasyflightgames.com/l5r/L5C04_56.jpg",
        "octgn_id": "3fdf3da1-12ee-4c94-b746-458b5aed0397",
        "position": "56",
        "quantity": 3
    },
    {
        "card_id": "benten-s-touch",
        "flavor": "\"Blessed Benten, Lady of Love and Beauty, shine your radiance upon me. Let my hands work your beauty in the mortal realm and my words spread your grace to all.\"",
        "illustrator": "Eli Ring",
        "image_url": "http://lcg-cdn.fantasyflightgames.com/l5r/L5C04_55.jpg",
        "octgn_id": "20fbf9fa-7702-44b1-acb8-5068d388251e",
        "position": "55",
        "quantity": 3
    },
    {
        "card_id": "censure",
        "flavor": "\"I bring word from the Imperial Chancellor.\"",
        "illustrator": "Ancor Gil Hernandez",
        "image_url": "http://lcg-cdn.fantasyflightgames.com/l5r/L5C04_60.jpg",
        "octgn_id": "ff8434e0-7363-4d38-8f2e-871113f1613b",
        "position": "60",
        "quantity": 3
    },
    {
        "card_id": "chasing-the-sun",
        "flavor": null,
        "illustrator": "Halil Ural",
        "image_url": "http://lcg-cdn.fantasyflightgames.com/l5r/L5C04_58.jpg",
        "octgn_id": "81a67e36-0a73-43f8-82e6-fabd67e71b56",
        "position": "58",
        "quantity": 3
    },
    {
        "card_id": "child-of-the-plains",
        "flavor": null,
        "illustrator": "Oscar Römer",
        "image_url": "http://lcg-cdn.fantasyflightgames.com/l5r/L5C04_48.jpg",
        "octgn_id": "99bea6e4-5ee4-48c9-b8a4-daf19fd96ea3",
        "position": "48",
        "quantity": 3
    },
    {
        "card_id": "chisei-district",
        "flavor": null,
        "illustrator": "Nele Diel",
        "image_url": "http://lcg-cdn.fantasyflightgames.com/l5r/L5C04_44.jpg",
        "octgn_id": "c8227c2c-aecf-4484-977f-8f1f1a5569cf",
        "position": "44",
        "quantity": 3
    },
    {
        "card_id": "enigmatic-magistrate",
        "flavor": "\"Is it just to uphold an unjust law?\"",
        "illustrator": "Ray Greaves",
        "image_url": "http://lcg-cdn.fantasyflightgames.com/l5r/L5C04_45.jpg",
        "octgn_id": "278f45b5-8563-4ce3-a000-1b24519f5cc0",
        "position": "45",
        "quantity": 3
    },
    {
        "card_id": "feast-or-famine",
        "flavor": "One man’s famine is another man’s feast.",
        "illustrator": "Filip Storch",
        "image_url": "http://lcg-cdn.fantasyflightgames.com/l5r/L5C04_41.jpg",
        "octgn_id": "edd24316-b484-4720-9e98-7e37d2c0ea43",
        "position": "41",
        "quantity": 3
    },
    {
        "card_id": "hiruma-skirmisher",
        "flavor": "\"My lord, I bring grave tidings from beyond the Wall.\"",
        "illustrator": "Pavel Tomashevskiy",
        "image_url": "http://lcg-cdn.fantasyflightgames.com/l5r/L5C04_50.jpg",
        "octgn_id": "e5381318-3c8c-4239-a00c-1dd6868a1964",
        "position": "50",
        "quantity": 3
    },
    {
        "card_id": "kakita-yoshi",
        "flavor": "\"I will not forget.\"",
        "illustrator": "Polar Engine",
        "image_url": "http://lcg-cdn.fantasyflightgames.com/l5r/L5C04_43.jpg",
        "octgn_id": "5c4a29c3-9405-4ca8-b666-1e5cf02a42bb",
        "position": "43",
        "quantity": 3
    },
    {
        "card_id": "mantra-of-water",
        "flavor": null,
        "illustrator": "Pavel Kolomeyets",
        "image_url": "http://lcg-cdn.fantasyflightgames.com/l5r/L5C04_52.jpg",
        "octgn_id": "d974750b-6699-419d-b49f-201a77c1dd43",
        "position": "52",
        "quantity": 3
    },
    {
        "card_id": "misinformation",
        "flavor": null,
        "illustrator": "Tropa Entertainment",
        "image_url": "http://lcg-cdn.fantasyflightgames.com/l5r/L5C04_57.jpg",
        "octgn_id": "92759058-ca1a-4117-901b-11b191e2b5ad",
        "position": "57",
        "quantity": 3
    },
    {
        "card_id": "prodigy-of-the-waves",
        "flavor": "\"To adapt and flow around any problem, this is the lesson of water.\" – Isawa’s Elements",
        "illustrator": "Le Vuong",
        "image_url": "http://lcg-cdn.fantasyflightgames.com/l5r/L5C04_46.jpg",
        "octgn_id": "3051ec67-f28b-490e-90c3-170ad8fb4de6",
        "position": "46",
        "quantity": 3
    },
    {
        "card_id": "public-forum",
        "flavor": null,
        "illustrator": "Pavel Kolomeyets",
        "image_url": "http://lcg-cdn.fantasyflightgames.com/l5r/L5C04_42.jpg",
        "octgn_id": "24e10db7-1638-48a8-be1b-5a11e553e19b",
        "position": "42",
        "quantity": 3
    },
    {
        "card_id": "seal-of-the-crab",
        "flavor": "In the name of Lord Hida Kisada, Defender of the Wall",
        "illustrator": "Mauro Dal Bo",
        "image_url": "http://lcg-cdn.fantasyflightgames.com/l5r/L5C04_51.jpg",
        "octgn_id": "3eb40e76-7454-4c62-8a70-c2195c43544e",
        "position": "51",
        "quantity": 3
    },
    {
        "card_id": "tattered-missive",
        "flavor": null,
        "illustrator": "Borja Pindado",
        "image_url": "http://lcg-cdn.fantasyflightgames.com/l5r/L5C04_59.jpg",
        "octgn_id": "cafd9d0a-1c5b-4593-b324-74538c21dc84",
        "position": "59",
        "quantity": 3
    },
    {
        "card_id": "test-of-courage",
        "flavor": null,
        "illustrator": "Nasrul Hakim",
        "image_url": "http://lcg-cdn.fantasyflightgames.com/l5r/L5C04_54.jpg",
        "octgn_id": "971a6787-f4e9-40e0-85d1-f197d91f490e",
        "position": "54",
        "quantity": 3
    },
    {
        "card_id": "war-dog-master",
        "flavor": "\"If samurai were as loyal as dogs, there would be no need for Bushidō.\"",
        "illustrator": "Calvin Chua",
        "image_url": "http://lcg-cdn.fantasyflightgames.com/l5r/L5C04_49.jpg",
        "octgn_id": "80f7220b-627c-4ff9-8db6-5896d8a9a292",
        "position": "49",
        "quantity": 3
    }
]
