[
    {
        "clan_code": "crane",
        "code": "daidoji-nerishma",
        "cost": 2,
        "deck_limit": 3,
        "element_code": null,
        "fate": null,
        "glory": 1,
        "honor": null,
        "illustrator": "Polar Engine",
        "influence_cost": null,
        "influence_pool": null,
        "is_unique": true,
        "keywords": "Bushi. Scout.",
        "military_strength": "3",
        "military_strength_mod": null,
        "name": "Daidoji Nerishma",
        "political_strength": "1",
        "political_strength_mod": null,
        "province_strength": null,
        "province_strength_mod": null,
        "side_code": "dynasty",
        "text": "<b>Action:<\/b> Choose a facedown card in one of your provinces – turn that card faceup.",
        "type_code": "character"
    }
]