[
    {
        "clan": "phoenix",
        "cost": 1,
        "deck_limit": 3,
        "element": null,
        "fate": null,
        "flavor": "\"Your first lesson is to realize that facts alone cannot sway the soul.\" - Asako Hayate",
        "glory": 2,
        "honor": null,
        "id": "naive-student",
        "illustrator": "Matt Hansen",
        "influence_cost": null,
        "influence_pool": null,
        "military": null,
        "military_bonus": null,
        "name": "Naive Student",
        "political": "2",
        "political_bonus": null,
        "position": 81,
        "side": "dynasty",
        "strength": null,
        "strength_bonus": null,
        "text": "Sincerity. <i>(When this character leaves play, draw 1 card.)</i>",
        "traits": [
            "courtier",
            "scholar"
        ],
        "type": "character",
        "unicity": false
    }
]