[
    {
        "clan_code": "crane",
        "code": "way-of-the-crane",
        "cost": 0,
        "element_code": null,
        "fate": null,
        "glory": null,
        "honor": null,
        "illustrator": "Scott Wade",
        "influence": null,
        "influence_cost": null,
        "is_conflict": true,
        "is_destiny": false,
        "is_unique": false,
        "keywords": "Philosophy.",
        "military_strength": null,
        "military_strength_mod": null,
        "name": "Way of the Crane",
        "political_strength": null,
        "political_strength_mod": null,
        "province_strength": null,
        "province_strength_mod": null,
        "text": "<b>Action:<\/b> Choose a [clan-crane] character you control – honor that character.",
        "type_code": "event"
    }
]