{
    "allowed_clans": [
        "*"
    ],
    "clan": "lion",
    "cost": 1,
    "deck_limit": 3,
    "elements": [
        null
    ],
    "fate": null,
    "glory": null,
    "honor": null,
    "id": "01-guidance-of-the-ancestors",
    "influence_cost": 1,
    "influence_pool": null,
    "is_restricted": false,
    "military": null,
    "military_bonus": "+1",
    "name": "Guidance of the Ancestors",
    "political": null,
    "political_bonus": "+1",
    "role_restriction": null,
    "side": "conflict",
    "strength": null,
    "strength_bonus": null,
    "text": "<b>Action:</b> Play this attachment from your conflict discard pile.",
    "traits": [
        "condition"
    ],
    "type": "attachment",
    "unique": false
}