{
    "allowed_clans": [
        "*"
    ],
    "clan": "crab",
    "cost": 0,
    "deck_limit": 3,
    "elements": [
        null
    ],
    "fate": null,
    "glory": null,
    "honor": null,
    "id": "23-withstand-the-darkness",
    "influence_cost": 1,
    "influence_pool": null,
    "is_restricted": false,
    "military": null,
    "military_bonus": null,
    "name": "Withstand the Darkness",
    "political": null,
    "political_bonus": null,
    "role_restriction": null,
    "side": "conflict",
    "strength": null,
    "strength_bonus": null,
    "text": "<b>Reaction:</b> After an opponent plays an event that chooses a [clan-crab] character you control as a target - place 1 fate on that character. (Max 1 per phase.)",
    "traits": [],
    "type": "event",
    "unique": false
}