{
    "allowed_clans": [
        "dragon"
    ],
    "clan": "dragon",
    "cost": 1,
    "deck_limit": 3,
    "elements": [
        null
    ],
    "fate": null,
    "glory": null,
    "honor": null,
    "id": "25-niten",
    "influence_cost": null,
    "influence_pool": null,
    "is_restricted": false,
    "military": null,
    "military_bonus": "+1",
    "name": "Niten",
    "political": null,
    "political_bonus": "+1",
    "role_restriction": null,
    "side": "conflict",
    "strength": null,
    "strength_bonus": null,
    "text": "Attach to a [clan-dragon] character.<br><b>Action:</b> During a conflict in which attached character is participating, return this attachment to your hand - put an attachment from your hand into play attached to the same character. (Max 1 per round.)",
    "traits": [
        "item",
        "philosophy"
    ],
    "type": "attachment",
    "unique": true
}