{
    "id": "30-spectral-visitation",
    "name": "Spectral Visitation",
    "cost": null,
    "text": "<b>Reaction:</b> After this province is revealed, discard the top 4 cards of your dynasty deck. Choose a character in your dynasty discard pile - put that character into play. If it is in play at the end of the phase, put it on the bottom of your dynasty deck.",
    "type": "province",
    "clan": "lion",
    "elements": [
        "earth"
    ],
    "isUnique": false,
    "side": "province",
    "traits": [
        "spirit"
    ],
    "military": null,
    "political": null,
    "strength": "4",
    "militaryBonus": null,
    "politicalBonus": null,
    "strengthBonus": null,
    "glory": null,
    "honor": null,
    "fate": null,
    "influencePool": null,
    "influenceCost": null,
    "deckLimit": 1,
    "roleRestriction": null
}