{
    "allowed_clans": [
        "*"
    ],
    "clan": "crane",
    "cost": 1,
    "deck_limit": 3,
    "elements": [],
    "fate": null,
    "glory": null,
    "honor": null,
    "id": "38-disparaging-challenge",
    "influence_cost": 2,
    "influence_pool": null,
    "is_unique": false,
    "military": null,
    "military_bonus": null,
    "name": "Disparaging Challenge",
    "political": null,
    "political_bonus": null,
    "role_restriction": null,
    "side": "conflict",
    "strength": null,
    "strength_bonus": null,
    "text": "<b>Action:</b> During a conflict, initiate a [conflict-political] duel against a character your opponent controls in their home area - resolve the duel. Move the duel's loser to the conflict, if able. Otherwise, move it home.",
    "traits": [],
    "type": "event"
}