[
    {
        "clan": "neutral",
        "cost": null,
        "deck_limit": 1,
        "element": null,
        "fate": null,
        "glory": null,
        "honor": null,
        "id": "miwaku-kabe",
        "influence_cost": null,
        "influence_pool": null,
        "military": null,
        "military_bonus": null,
        "name": "Miwaku Kabe",
        "name_extra": null,
        "political": null,
        "political_bonus": null,
        "role_restriction": null,
        "side": "dynasty",
        "strength": null,
        "strength_bonus": "+3",
        "text": "Limit 1 per deck.\n<b>Interrupt:</b> When this holding's province is broken – shuffle this card back into your dynasty deck.",
        "traits": [
            "imperial"
        ],
        "type": "holding",
        "unicity": true
    }
]
